thirdparty/__init__.py
thirdparty/yaml/__init__.py
thirdparty/yaml/overlay.py
thirdparty/yaml/utils.py
thirdparty/yaml/include/__init__.py
thirdparty/yaml/include/format/__init__.py
thirdparty/yaml/include/format/verbatim.py
thirdparty/yaml/include/format/xml.py
thirdparty/yaml/include/format/yaml.py
thirdparty/yaml/include/scheme/__init__.py
thirdparty/yaml/include/scheme/file.py
thirdparty/yaml/include/scheme/pyenv.py
thirdparty/yaml/include/scheme/url.py
thirdparty/yaml/operation/__init__.py
thirdparty/yaml/operation/add.py
thirdparty/yaml/operation/delete.py
thirdparty/yaml/operation/merge.py
thirdparty/yaml/tests/__init__.py
thirdparty/yaml/tests/test_dump.py
thirdparty/yaml/tests/test_load.py
thirdparty/yaml/tests/data/test_include_recursive_merge.yaml
thirdparty/yaml/tests/data/test_include_url.yaml
thirdparty/yaml/tests/data/test_include_verbatim.yaml
thirdparty/yaml/tests/data/test_simple_mapping.yaml
thirdparty/yaml/tests/data/test_simple_text.txt
thirdparty_yaml-0.1.0.dist-info/LICENSE
thirdparty_yaml-0.1.0.dist-info/METADATA
thirdparty_yaml-0.1.0.dist-info/WHEEL
thirdparty_yaml-0.1.0.dist-info/top_level.txt
thirdparty_yaml-0.1.0.dist-info/RECORD
