Metadata-Version: 2.1
Name: thirdparty-yaml
Version: 0.1.0
Summary: Tools for managing yaml configurations.
Home-page: https://github.com/third-party-dev/yaml
Author: Vincent Agriesti
Author-email: crazychenz@gmail.com
License: UNKNOWN
Platform: UNKNOWN
Classifier: Programming Language :: Python :: 3
Classifier: Intended Audience :: Developers
Classifier: License :: OSI Approved :: MIT License
Classifier: Operating System :: OS Independent
Classifier: Topic :: Software Development :: Build Tools
Classifier: Topic :: Software Development :: Compilers
Classifier: Topic :: Software Development :: Pre-processors
Classifier: Topic :: Utilities
Requires-Python: ~=3.7
Requires-Dist: future
Requires-Dist: pkg-resources
Requires-Dist: ruamel.yaml
